helx_base/__init__.py
helx_base/_version.py
helx_base/config.py
helx_base/image.py
helx_base/mdp.py
helx_base/modules.py
helx_base/spaces.py
HELX_base-1.0.0.dist-info/AUTHORS
HELX_base-1.0.0.dist-info/LICENSE
HELX_base-1.0.0.dist-info/METADATA
HELX_base-1.0.0.dist-info/NOTICE
HELX_base-1.0.0.dist-info/WHEEL
HELX_base-1.0.0.dist-info/top_level.txt
HELX_base-1.0.0.dist-info/RECORD
